reveal_yaml/__init__.py
reveal_yaml/__main__.py
reveal_yaml/blank.yaml
reveal_yaml/deploy.yaml
reveal_yaml/editor.py
reveal_yaml/py.typed
reveal_yaml/reveal.yaml
reveal_yaml/schema.json
reveal_yaml/schema.yaml
reveal_yaml/slides.py
reveal_yaml/slides_app.py
reveal_yaml/utility.py
reveal_yaml/static/ace/ace.min.js
reveal_yaml/static/ace/ext-language_tools.min.js
reveal_yaml/static/ace/ext-searchbox.min.js
reveal_yaml/static/ace/ext-whitespace.min.js
reveal_yaml/static/ace/js-yaml.min.js
reveal_yaml/static/ace/mode-yaml.min.js
reveal_yaml/static/ace/theme-chrome.min.js
reveal_yaml/static/ace/theme-monokai.min.js
reveal_yaml/static/img/icon.png
reveal_yaml/static/img/watermark.png
reveal_yaml/static/js/jquery.min.js
reveal_yaml/static/plugin/highlight/highlight.js
reveal_yaml/static/plugin/highlight/monokai.css
reveal_yaml/static/plugin/highlight/zenburn.css
reveal_yaml/static/plugin/markdown/markdown.js
reveal_yaml/static/plugin/math/math.js
reveal_yaml/static/plugin/notes/notes.js
reveal_yaml/static/plugin/notes/speaker-view.html
reveal_yaml/static/plugin/search/search.js
reveal_yaml/static/plugin/zoom/zoom.js
reveal_yaml/static/reveal.js/reset.css
reveal_yaml/static/reveal.js/reveal.css
reveal_yaml/static/reveal.js/reveal.js
reveal_yaml/static/reveal.js/reveal.js.map
reveal_yaml/static/reveal.js/theme/beige.css
reveal_yaml/static/reveal.js/theme/black.css
reveal_yaml/static/reveal.js/theme/blood.css
reveal_yaml/static/reveal.js/theme/league.css
reveal_yaml/static/reveal.js/theme/moon.css
reveal_yaml/static/reveal.js/theme/night.css
reveal_yaml/static/reveal.js/theme/serif.css
reveal_yaml/static/reveal.js/theme/simple.css
reveal_yaml/static/reveal.js/theme/sky.css
reveal_yaml/static/reveal.js/theme/solarized.css
reveal_yaml/static/reveal.js/theme/white.css
reveal_yaml/static/reveal.js/theme/fonts/league-gothic/LICENSE
reveal_yaml/static/reveal.js/theme/fonts/league-gothic/league-gothic.css
reveal_yaml/static/reveal.js/theme/fonts/league-gothic/league-gothic.eot
reveal_yaml-2.4.0.dist-info/LICENSE
reveal_yaml-2.4.0.dist-info/METADATA
reveal_yaml-2.4.0.dist-info/WHEEL
reveal_yaml-2.4.0.dist-info/entry_points.txt
reveal_yaml-2.4.0.dist-info/top_level.txt
reveal_yaml-2.4.0.dist-info/RECORD
